finvader/Henry.py
finvader/SentiBignomics.py
finvader/__init__.py
finvader/finvader.py
finvader-1.0.4.dist-info/LICENSE
finvader-1.0.4.dist-info/METADATA
finvader-1.0.4.dist-info/WHEEL
finvader-1.0.4.dist-info/top_level.txt
finvader-1.0.4.dist-info/RECORD
