Metadata-Version: 2.1
Name: finvader
Version: 1.0.4
Summary: VADER sentiment classifier updated with financial lexicons
Home-page: https://github.com/PetrKorab/FinVADER
Author: Petr Koráb
Author-email: xpetrkorab@gmail.com
License: OSI Approved :: Apache Software License
Requires-Python: >=3.8, <3.12
License-File: LICENSE
Requires-Dist: nltk ==3.6.2
